Metadata-Version: 2.4
Name: djangorestframework-guardian
Version: 0.4.0
Summary: django-guardian support for Django REST Framework
Author-email: Ryan P Kilby <kilbyr@gmail.com>
License-Expression: BSD-3-Clause
Project-URL: Repository, https://github.com/rpkilby/django-rest-framework-guardian
Project-URL: Issues, https://github.com/rpkilby/django-rest-framework-guardian/issues
Project-URL: Changelog, https://github.com/rpkilby/django-rest-framework-guardian/CHANGELOG
Classifier: Development Status :: 5 - Production/Stable
Classifier: Environment :: Web Environment
Classifier: Framework :: Django
Classifier: Framework :: Django :: 4.2
Classifier: Framework :: Django :: 5.0
Classifier: Framework :: Django :: 5.1
Classifier: Framework :: Django :: 5.2
Classifier: Intended Audience :: Developers
Classifier: Operating System :: OS Independent
Classifier: Programming Language :: Python :: 3 :: Only
Classifier: Programming Language :: Python :: 3.10
Classifier: Programming Language :: Python :: 3.11
Classifier: Programming Language :: Python :: 3.12
Classifier: Programming Language :: Python :: 3.13
Requires-Python: >=3.10
License-File: LICENSE
Requires-Dist: django
Requires-Dist: djangorestframework
Requires-Dist: django-guardian
Dynamic: license-file
